htmligator/__init__.py
htmligator/cli.py
htmligator/exception.py
htmligator/html.py
htmligator/htmligator.py
htmligator/util.py
htmligator-0.11.0.dist-info/METADATA
htmligator-0.11.0.dist-info/WHEEL
htmligator-0.11.0.dist-info/entry_points.txt
htmligator-0.11.0.dist-info/licenses/LICENSE
htmligator-0.11.0.dist-info/RECORD
