Metadata-Version: 2.4
Name: htmligator
Version: 0.11.0
Summary: generate wrapper html files to navigate folder contents
License: MIT
License-File: LICENSE
Keywords: downloader
Author: Siak Hooi
Author-email: siakhooi@gmail.com
Requires-Python: >=3.10
Classifier: Development Status :: 4 - Beta
Classifier: Environment :: Console
Classifier: License :: OSI Approved :: MIT License
Classifier: Topic :: Utilities
Requires-Dist: natsort (>=8.4.0,<9.0.0)
Project-URL: Bug Tracker, https://github.com/siakhooi/python-htmligator/issues
Project-URL: Documentation, https://github.com/siakhooi/python-htmligator/wiki
Project-URL: Homepage, https://github.com/siakhooi/python-htmligator
Project-URL: Repository, https://github.com/siakhooi/python-htmligator
